settings.py
canvas_cli/__init__.py
canvas_cli/main.py
canvas_cli/apps/__init__.py
canvas_cli/apps/auth/__init__.py
canvas_cli/apps/auth/storage.py
canvas_cli/apps/auth/utils.py
canvas_cli/apps/emit/__init__.py
canvas_cli/apps/emit/emit.py
canvas_cli/apps/emit/event_fixtures/ALLERGY_INTOLERANCE_CREATED.ndjson
canvas_cli/apps/emit/event_fixtures/ALLERGY_INTOLERANCE_UPDATED.ndjson
canvas_cli/apps/emit/event_fixtures/APPOINTMENT_CANCELED.ndjson
canvas_cli/apps/emit/event_fixtures/APPOINTMENT_CHECKED_IN.ndjson
canvas_cli/apps/emit/event_fixtures/APPOINTMENT_CREATED.ndjson
canvas_cli/apps/emit/event_fixtures/APPOINTMENT_NO_SHOWED.ndjson
canvas_cli/apps/emit/event_fixtures/APPOINTMENT_RESCHEDULED.ndjson
canvas_cli/apps/emit/event_fixtures/APPOINTMENT_RESTORED.ndjson
canvas_cli/apps/emit/event_fixtures/APPOINTMENT_UPDATED.ndjson
canvas_cli/apps/emit/event_fixtures/ASSESS_COMMAND__CONDITION_SELECTED.ndjson
canvas_cli/apps/emit/event_fixtures/ASSESS_COMMAND__POST_COMMIT.ndjson
canvas_cli/apps/emit/event_fixtures/ASSESS_COMMAND__POST_ORIGINATE.ndjson
canvas_cli/apps/emit/event_fixtures/ASSESS_COMMAND__POST_UPDATE.ndjson
canvas_cli/apps/emit/event_fixtures/ASSESS_COMMAND__PRE_COMMIT.ndjson
canvas_cli/apps/emit/event_fixtures/ASSESS_COMMAND__PRE_ORIGINATE.ndjson
canvas_cli/apps/emit/event_fixtures/ASSESS_COMMAND__PRE_UPDATE.ndjson
canvas_cli/apps/emit/event_fixtures/BILLING_LINE_ITEM_CREATED.ndjson
canvas_cli/apps/emit/event_fixtures/BILLING_LINE_ITEM_UPDATED.ndjson
canvas_cli/apps/emit/event_fixtures/CONDITION_ASSESSED.ndjson
canvas_cli/apps/emit/event_fixtures/CONDITION_CREATED.ndjson
canvas_cli/apps/emit/event_fixtures/CONDITION_UPDATED.ndjson
canvas_cli/apps/emit/event_fixtures/CRON.ndjson
canvas_cli/apps/emit/event_fixtures/ENCOUNTER_CREATED.ndjson
canvas_cli/apps/emit/event_fixtures/ENCOUNTER_UPDATED.ndjson
canvas_cli/apps/emit/event_fixtures/IMMUNIZATION_CREATED.ndjson
canvas_cli/apps/emit/event_fixtures/IMMUNIZATION_STATEMENT_CREATED.ndjson
canvas-0.94.0.dist-info/METADATA
canvas-0.94.0.dist-info/WHEEL
canvas-0.94.0.dist-info/entry_points.txt
canvas-0.94.0.dist-info/RECORD
